zoopipe/__init__.py
zoopipe/core.py
zoopipe/hooks/__init__.py
zoopipe/hooks/base.py
zoopipe/input_adapter/__init__.py
zoopipe/input_adapter/arrow.py
zoopipe/input_adapter/base.py
zoopipe/input_adapter/csv.py
zoopipe/input_adapter/duckdb.py
zoopipe/input_adapter/json.py
zoopipe/input_adapter/parquet.py
zoopipe/input_adapter/pygen.py
zoopipe/input_adapter/sql.py
zoopipe/output_adapter/__init__.py
zoopipe/output_adapter/arrow.py
zoopipe/output_adapter/base.py
zoopipe/output_adapter/csv.py
zoopipe/output_adapter/duckdb.py
zoopipe/output_adapter/json.py
zoopipe/output_adapter/parquet.py
zoopipe/output_adapter/pygen.py
zoopipe/output_adapter/sql.py
zoopipe/report.py
zoopipe/zoopipe_rust_core.abi3.so
zoopipe-2026.1.14.dist-info/METADATA
zoopipe-2026.1.14.dist-info/WHEEL
zoopipe-2026.1.14.dist-info/licenses/LICENSE
zoopipe-2026.1.14.dist-info/RECORD
