Metadata-Version: 2.4
Name: zoopipe
Version: 2026.1.14
Requires-Dist: pydantic>=2.12.5
License-File: LICENSE
Summary: ZooPipe is a data processing framework that allows you to process data in a declarative way.
Author-email: Alberto Daniel Badia <alberto_badia@enlacepatagonia.com>
Requires-Python: >=3.10, <3.14
Project-URL: Homepage, https://github.com/albertobadia/zoopipe
